imo_vmdb/__init__.py
imo_vmdb/__main__.py
imo_vmdb/command/__init__.py
imo_vmdb/command/cleanup.py
imo_vmdb/command/import_csv.py
imo_vmdb/command/initdb.py
imo_vmdb/command/normalize.py
imo_vmdb/csv_import/__init__.py
imo_vmdb/csv_import/magnitudes.py
imo_vmdb/csv_import/radiant.py
imo_vmdb/csv_import/rate.py
imo_vmdb/csv_import/session.py
imo_vmdb/csv_import/shower.py
imo_vmdb/data/radiants.csv
imo_vmdb/data/showers.csv
imo_vmdb/db.py
imo_vmdb/model/__init__.py
imo_vmdb/model/radiant.py
imo_vmdb/model/shower.py
imo_vmdb/model/sky.py
imo_vmdb/normalizer/__init__.py
imo_vmdb/normalizer/magnitude.py
imo_vmdb/normalizer/rate.py
imo_vmdb/normalizer/session.py
imo_vmdb-1.4.0.dist-info/LICENSE.txt
imo_vmdb-1.4.0.dist-info/METADATA
imo_vmdb-1.4.0.dist-info/WHEEL
imo_vmdb-1.4.0.dist-info/RECORD
