Metadata-Version: 2.1
Name: imo-vmdb
Version: 1.4.0
Summary: Imports VMDB CSV files from IMO into a SQL database.
Home-page: https://github.com/jankorichter/imo-vmdb
License: MIT
Keywords: IMO,VMDB,SQL
Author: Janko Richter
Author-email: janko@richtej.de
Requires-Python: >=3.8,<4.0
Classifier: License :: OSI Approved :: MIT License
Classifier: Operating System :: OS Independent
Classifier: Programming Language :: Python :: 3
Classifier: Programming Language :: Python :: 3.8
Classifier: Programming Language :: Python :: 3.9
Classifier: Programming Language :: Python :: 3.10
Classifier: Programming Language :: Python :: 3.11
Classifier: Programming Language :: Python :: 3.12
Provides-Extra: docs
Provides-Extra: mysql
Provides-Extra: pgsql
Requires-Dist: Sphinx (>=4.2,<5.0) ; extra == "docs"
Requires-Dist: astropy (>=5.2,<6.0)
Requires-Dist: psycopg2 (>=2.9,<3.0) ; extra == "pgsql"
Requires-Dist: pymysql (>=1.0,<2.0) ; extra == "mysql"
Requires-Dist: sphinx-rtd-theme (>=1.0,<2.0) ; extra == "docs"
Project-URL: Bug Tracker, https://github.com/jankorichter/imo-vmdb/issues
Project-URL: Documentation, https://imo-vmdb.readthedocs.io/en/latest/
Project-URL: Repository, https://github.com/jankorichter/imo-vmdb
